{
  "latitude": 50.08,
  "longitude": 14.419998,
  "generationtime_ms": 0.03993511199951172,
  "utc_offset_seconds": 0,
  "timezone": "GMT",
  "timezone_abbreviation": "GMT",
  "elevation": 205.0,
  "hourly_units": {
    "time": "unixtime",
    "temperature_2m": "\u00b0C",
    "shortwave_radiation": "W/m\u00b2"
  },
  "hourly": {
    "time": [
      0,
      0,
      0,
      0,
      0,
      0,
      0,
      0,
      0,
      0,
      0,
      0,
      0,
      0,
      0,
      0,
      0,
      0,
      0,
      0,
      0,
      0,
      0,
      0
    ],
    "temperature_2m": [
      14.950000000000001,
      14.8,
      14.65,
      14.850000000000001,
      15.4,
      15.4,
      15.8,
      16.900000000000002,
      18.25,
      19.650000000000002,
      20.950000000000003,
      22.0,
      22.5,
      22.75,
      22.650000000000002,
      22.450000000000003,
      22.200000000000003,
      21.6,
      21.0,
      20.450000000000003,
      19.900000000000002,
      19.25,
      18.5,
      17.7
    ],
    "shortwave_radiation": [
      0.0,
      0.0,
      0.0,
      0.0,
      0.0,
      7.2,
      162.0,
      468.0,
      784.8000000000001,
      990.0,
      1242.0,
      1296.0,
      961.2,
      997.2,
      637.2,
      684.0,
      316.8,
      140.4,
      190.8,
      54.0,
      18.0,
      0.0,
      0.0,
      0.0
    ]
  }
}